<sect1 id="Beleaguered Castle">  <!--<sect1info>
    <copyright>
      <year>2001</year>
      <holder>Rosanna Yuen</holder>
    </copyright>
    <author>
      <firstname>Rosanna</firstname>
      <surname>Yuen</surname>
    </author>
    <address><email>zana@webwynk.net</email></address>
		<copyright>
			<year>2004</year>
			<holder>Damien Laniel</holder>
		</copyright>
		<author>
			<firstname>Damien</firstname>
			<surname>Laniel</surname>
		</author>
		<address><email>heretik@tuxfamily.org</email></address>
  </sect1info>-->

  <title>Le château assiégé</title>

  <para>Ecrit par Rosanna Yuen</para>
  <para>Traduit en français par Damien Laniel</para>

  <sect2>Configuration</sect2>

  <informaltable>
    <tgroup cols="2">
      <tbody>
	<row>
		<entry>Type de Paquet</entry>
		<entry>Paquet Standard</entry>
	</row>
	<row>
	  <entry>Foundations</entry>
	  <entry>
	  	Quatre piles dans la colonne du milieu. Quatre As y sont placés, un sur
	  	chaque pile, avant de mélanger. A contruire de l'As au Roi.
	  	Les cartes du dessus de chaque fondation peuvent être rejouées sur le
	  	tableau.
	  </entry>
	</row>
	<row>
	  <entry>Tableau</entry>
	  <entry>
	  	Huit piles, quatre à gauche des fondations et quatre à droite.
	  	Toutes les cartes sont distribuées face visible sur huit piles,
	  	de telle sorte qu'il y a ait six cartes sur chaque pile.
	  </entry>
	</row>
      </tbody>
    </tgroup>
  </informaltable>

  <sect2>Objectif</sect2>

  <para>
  	Déplacer toutes les cartes vers les fondations.
  </para>

  <sect2>Règles</sect2>
  <para>
  	Les piles du tableau sont construites en descendant quelque soit les suites.
  	Une seule carte peut être déplacée à la fois. Les piles vides peuvent être
  	remplies avec n'importe quelle carte.
  </para>
  <para>
  	Les fondations sont construites par suite.
  </para>

  <sect2>Options</sect2>
  <para>Aucune</para>

  <sect2>Score</sect2>
  <para>
  	Chaque carte dans les fondation, excepté les As d'origine, comptent un point.
  </para>
  <para>
  	Score maximum possible : 48
  </para>

  <sect2>Stratégie</sect2>
  <para>
  	Construisez de façon égale sur les fondations si possible.
  	Essayez de libérez une pile du tableau.
  </para>
</sect1>
